yabin/__init__.py
yabin/cli.py
yabin/client.py
yabin/crypto.py
yabin-0.1.1.dist-info/METADATA
yabin-0.1.1.dist-info/WHEEL
yabin-0.1.1.dist-info/entry_points.txt
yabin-0.1.1.dist-info/RECORD
